pyrhyme.py
pyrhyme-0.1.dist-info/METADATA
pyrhyme-0.1.dist-info/WHEEL
pyrhyme-0.1.dist-info/top_level.txt
pyrhyme-0.1.dist-info/RECORD
