Metadata-Version: 2.1
Name: pyrhyme
Version: 0.1
Summary: Python wrapper for RhymeBrain API
Home-page: https://github.com/GSejas/pyrhyme/
Author: Jorge Sequeira
Author-email: jsequeira03@gmail.com
License: MIT
Keywords: python rhyme words api
Platform: UNKNOWN
Classifier: Development Status :: 4 - Beta
Classifier: Intended Audience :: Developers
Classifier: License :: OSI Approved :: MIT License
Classifier: Operating System :: OS Independent
Classifier: Programming Language :: Python
Classifier: Topic :: Software Development :: Libraries :: Python Modules
Requires-Dist: requests
